picviewer/__init__.py
picviewer/__main__.py
picviewer/__version__.py
picviewer/configuration/__init__.py
picviewer/configuration/config_loadsave.py
picviewer/controller/__init__.py
picviewer/controller/combobox_controller.py
picviewer/controller/greeting.py
picviewer/controller/initialization.py
picviewer/controller/main_controller.py
picviewer/controller/mainwindow.py
picviewer/controller/mouse_controller.py
picviewer/controller/panel_controller.py
picviewer/controller/slice_controller.py
picviewer/controller/space_controller.py
picviewer/controller/time_controller.py
picviewer/dataloader/__init__.py
picviewer/dataloader/data_collector.py
picviewer/dataloader/get_datainfo.py
picviewer/dataloader/get_openpmdinfo.py
picviewer/dataloader/get_warpxinfo.py
picviewer/dataloader/load_openpmd.py
picviewer/dataloader/load_tristanmp.py
picviewer/dataloader/load_warpx.py
picviewer/dataplotter/__init__.py
picviewer/dataplotter/cic_histogram.py
picviewer/dataplotter/makelocalplot.py
picviewer/dataplotter/makeplot.py
picviewer/dataplotter/prepare_localplot.py
picviewer/dataplotter/prepare_plot.py
picviewer/dataplotter/subwindow.py
picviewer/images/logo.png
picviewer/ui_files/__init__.py
picviewer/ui_files/base.ui
picviewer/ui_files/subwindow.ui
PICviewer-1.3.0.dist-info/LICENSE.txt
PICviewer-1.3.0.dist-info/METADATA
PICviewer-1.3.0.dist-info/WHEEL
PICviewer-1.3.0.dist-info/entry_points.txt
PICviewer-1.3.0.dist-info/top_level.txt
PICviewer-1.3.0.dist-info/RECORD
