Metadata-Version: 2.1
Name: PICviewer
Version: 1.3.0
Summary: PyQt-based visualization tools for PIC simulations
Home-page: https://bitbucket.org/ecp_warpx/picviewer/src/master/
Author: Jaehong Park
Author-email: jaehongpark@lbl.gov
License: UNKNOWN
Platform: UNKNOWN
Requires-Dist: numpy
Requires-Dist: h5py
Requires-Dist: numba
